vengeance_currency_api/__init__.py
vengeance_currency_api/api.py
vengeance_currency_api-2.2.0.dist-info/LICENSE
vengeance_currency_api-2.2.0.dist-info/METADATA
vengeance_currency_api-2.2.0.dist-info/WHEEL
vengeance_currency_api-2.2.0.dist-info/top_level.txt
vengeance_currency_api-2.2.0.dist-info/RECORD
