Metadata-Version: 2.1
Name: vengeance-currency-api
Version: 2.2.0
Summary: Library for currencies of countries across the world.
Home-page: https://github.com/preetham-1811/currency-api
Author: Preetham Kamishetty
Author-email: kamishettypreetham@gmail.com
Classifier: Programming Language :: Python :: 3
Classifier: License :: OSI Approved :: MIT License
Classifier: Operating System :: OS Independent
Requires-Python: >=3.6
License-File: LICENSE
Requires-Dist: Flask
